planc/__init__.py
planc/_common.py
planc/core_chatgpt.py
planc/core_deepseek.py
planc/core_doubao.py
planc/core_junie.py
planc/core_tongyi.py
planc/main.py
planc/py.typed
planc-0.0.1.dev20251226222400.dist-info/WHEEL
planc-0.0.1.dev20251226222400.dist-info/METADATA
planc-0.0.1.dev20251226222400.dist-info/RECORD
