Metadata-Version: 2.3
Name: planc
Version: 0.0.1.dev20251226222400
Summary: Add your description here
Requires-Dist: pydantic>=2.12.5
Requires-Dist: requests>=2.32.5
Requires-Dist: tencentcloud-sdk-python-common>=3.1.12
Requires-Dist: tencentcloud-sdk-python-cvm>=3.1.2
Requires-Dist: tencentcloud-sdk-python-vpc>=3.1.11
